MANIFEST.in
setup.py
tethne/__init__.py
tethne/__main__.py
tethne/utilities.py
tethne.egg-info/PKG-INFO
tethne.egg-info/SOURCES.txt
tethne.egg-info/dependency_links.txt
tethne.egg-info/requires.txt
tethne.egg-info/top_level.txt
tethne/analyze/__init__.py
tethne/analyze/collection.py
tethne/analyze/corpus.py
tethne/analyze/features.py
tethne/analyze/graph.py
tethne/bin/__init__.py
tethne/bin/mallet-2.0.7/LICENSE
tethne/bin/mallet-2.0.7/Makefile
tethne/bin/mallet-2.0.7/build.xml
tethne/bin/mallet-2.0.7/pom.xml
tethne/bin/mallet-2.0.7/bin/classifier2info
tethne/bin/mallet-2.0.7/bin/csv2classify
tethne/bin/mallet-2.0.7/bin/csv2vectors
tethne/bin/mallet-2.0.7/bin/mallet
tethne/bin/mallet-2.0.7/bin/mallet.bat
tethne/bin/mallet-2.0.7/bin/mallethon
tethne/bin/mallet-2.0.7/bin/prepend-license.sh
tethne/bin/mallet-2.0.7/bin/svmlight2vectors
tethne/bin/mallet-2.0.7/bin/text2classify
tethne/bin/mallet-2.0.7/bin/text2vectors
tethne/bin/mallet-2.0.7/bin/vectors2classify
tethne/bin/mallet-2.0.7/bin/vectors2info
tethne/bin/mallet-2.0.7/bin/vectors2topics
tethne/bin/mallet-2.0.7/bin/vectors2vectors
tethne/bin/mallet-2.0.7/class/cc/mallet/classify/AdaBoost.class
tethne/bin/mallet-2.0.7/class/cc/mallet/classify/AdaBoostM2.class
tethne/bin/mallet-2.0.7/class/cc/mallet/classify/AdaBoostM2Trainer.class
tethne/bin/mallet-2.0.7/class/cc/mallet/classify/AdaBoostTrainer.class
tethne/bin/mallet-2.0.7/class/cc/mallet/classify/BaggingClassifier.class
tethne/bin/mallet-2.0.7/class/cc/mallet/classify/BaggingTrainer.class
tethne/bin/mallet-2.0.7/class/cc/mallet/classify/BalancedWinnow.class
tethne/bin/mallet-2.0.7/class/cc/mallet/classify/BalancedWinnowTrainer.class
tethne/bin/mallet-2.0.7/class/cc/mallet/classify/Boostable.class
tethne/bin/mallet-2.0.7/class/cc/mallet/classify/C45$Node.class
tethne/bin/mallet-2.0.7/class/cc/mallet/classify/C45.class
tethne/bin/mallet-2.0.7/class/cc/mallet/classify/C45Trainer.class
tethne/bin/mallet-2.0.7/class/cc/mallet/classify/Classification.class
tethne/bin/mallet-2.0.7/class/cc/mallet/classify/Classifier.class
tethne/bin/mallet-2.0.7/class/cc/mallet/classify/ClassifierAccuracyEvaluator.class
