Metadata-Version: 1.0
Name: tethne
Version: 0.8
Summary: Bibliographic network and corpus analysis for historians
Home-page: http://diging.github.io/tethne/
Author: Erick Peirson
Author-email: erick [dot] peirson [at] asu [dot] edu
License: GNU GPL 3
Platform: UNKNOWN
